neil_vst/__init__.py
neil_vst/cli_script.py
neil_vst/logger.c
neil_vst/logger.cp39-win_amd64.pyd
neil_vst/vst_chain_worker.c
neil_vst/vst_chain_worker.cp39-win_amd64.pyd
neil_vst/vst_exceptions.c
neil_vst/vst_exceptions.cp39-win_amd64.pyd
neil_vst/vst_host.c
neil_vst/vst_host.cp39-win_amd64.pyd
neil_vst/vst_plugin.c
neil_vst/vst_plugin.cp39-win_amd64.pyd
neil_vst-0.2.7.dist-info/LICENSE
neil_vst-0.2.7.dist-info/METADATA
neil_vst-0.2.7.dist-info/WHEEL
neil_vst-0.2.7.dist-info/entry_points.txt
neil_vst-0.2.7.dist-info/top_level.txt
neil_vst-0.2.7.dist-info/RECORD
