Metadata-Version: 2.1
Name: neil-vst
Version: 0.2.7
Summary: Cython-based simple VST 2.4 Host and VST Plugins wrapper. Fast work and clean python object-oriented interface
Home-page: https://github.com/LeftRadio/py-neil-vst
Author: Vladislav Kamenev
Author-email: 
License: MIT
Keywords: vst,plugin,cython
Platform: UNKNOWN
Classifier: Development Status :: 4 - Beta
Classifier: Intended Audience :: Developers
Classifier: License :: OSI Approved :: MIT License
Classifier: Programming Language :: Python :: 3
Classifier: Programming Language :: Python :: 3.7
Classifier: Programming Language :: Python :: 3.8
Classifier: Programming Language :: Python :: 3.9
Requires-Dist: Cython (>=0.29.19)
Requires-Dist: SoundFile (>=0.10.3.post1)
Requires-Dist: numpy (==1.19.0)
